MANIFEST.in
setup.py
ristretto/__init__.py
ristretto.egg-info/PKG-INFO
ristretto.egg-info/SOURCES.txt
ristretto.egg-info/dependency_links.txt
ristretto.egg-info/requires.txt
ristretto.egg-info/top_level.txt
ristretto/dmd/__init__.py
ristretto/dmd/dmd.py
ristretto/dmd/rdmd.py
ristretto/dmd/rdmd_single.py
ristretto/mf/__init__.py
ristretto/mf/csvd.py
ristretto/mf/interp_decomp.py
ristretto/mf/rcur.py
ristretto/mf/rlu.py
ristretto/mf/rqb.py
ristretto/mf/rsvd.py
ristretto/mf/rsvd_single.py
ristretto/nmf/__init__.py
ristretto/nmf/_fhals_update.c
ristretto/nmf/_fhals_update.pyx
ristretto/nmf/_rfhals_update.c
ristretto/nmf/_rfhals_update.pyx
ristretto/nmf/nmf_fhals.py
ristretto/nmf/rnmf_fhals.py
ristretto/util/__init__.py
ristretto/util/data.py